pyny/__init__.py
pyny/api.py
pyny/fields.py
pyny/models.py
pyny-1.1.0.dist-info/DESCRIPTION.rst
pyny-1.1.0.dist-info/METADATA
pyny-1.1.0.dist-info/metadata.json
pyny-1.1.0.dist-info/RECORD
pyny-1.1.0.dist-info/top_level.txt
pyny-1.1.0.dist-info/WHEEL
