Metadata-Version: 2.0
Name: pyny
Version: 1.1.0
Summary: Python wrapper around the Nagareyama Open Data Web API
Home-page: https://github.com/7pairs/pyny
Author: Jun-ya HASEBA
Author-email: 7pairs@gmail.com
License: Apache License, Version 2.0
Keywords: web,api,opendata,nagareyama
Platform: UNKNOWN
Classifier: Development Status :: 5 - Production/Stable
Classifier: License :: OSI Approved :: Apache Software License
Classifier: Programming Language :: Python
Classifier: Programming Language :: Python :: 3
Classifier: Programming Language :: Python :: 3.2
Classifier: Programming Language :: Python :: 3.3
Classifier: Programming Language :: Python :: 3.4
Classifier: Topic :: Internet
